MANIFEST.in
README.md
setup.cfg
setup.py
file_split_merge/__init__.py
file_split_merge/file_split_merge.py
file_split_merge/fsm_cli.py
file_split_merge.egg-info/PKG-INFO
file_split_merge.egg-info/SOURCES.txt
file_split_merge.egg-info/dependency_links.txt
file_split_merge.egg-info/entry_points.txt
file_split_merge.egg-info/top_level.txt