Metadata-Version: 2.1
Name: file-split-merge
Version: 1.0.0
Summary: Commandline scripts to split or merge files
Home-page: http://github.com/roshanok/file_split_merge/
Author: Roshan Krishnappa
Author-email: roshan.ok@gmail.com
License: BSD
Platform: UNKNOWN
Classifier: Intended Audience :: Developers
Classifier: License :: OSI Approved :: BSD License
Classifier: Operating System :: OS Independent
Classifier: Programming Language :: Python
Classifier: Programming Language :: Python :: 3
